Metadata-Version: 2.1
Name: julia-semver
Version: 0.1.3
Summary: Julia version specifier format implementation
License: MIT
Project-URL: Home, http://github.com/jlapeyre/julia_semver
Platform: UNKNOWN
Classifier: Framework :: Django
Classifier: License :: OSI Approved :: MIT License
Classifier: Programming Language :: Python :: 3
License-File: LICENSE
